{
  "genesis_time": "2026-03-22T23:36:52.525Z",
  "chain_id": "ensoul-1",
  "initial_height": "1",
  "consensus_params": {
    "block": {
      "max_bytes": "67108864",
      "max_gas": "-1"
    },
    "evidence": {
      "max_age_num_blocks": "100000",
      "max_age_duration": "172800000000000",
      "max_bytes": "1048576"
    },
    "validator": {
      "pub_key_types": [
        "ed25519"
      ]
    },
    "version": {
      "app": "1"
    },
    "abci": {
      "vote_extensions_enable_height": "0"
    }
  },
  "validators": [
    {
      "address": "81CC3F39F9A1CB32B00DA9BA3E69825CFC6EBE64",
      "pub_key": {
        "type": "tendermint/PubKeyEd25519",
        "value": "Pmx2bUHzFe1XMvRhJ4UAC89pUwwWrOZLANorx43a+No="
      },
      "power": "4285724",
      "name": "mbp-v0"
    },
    {
      "address": "4FADBCFFB13896F39A23F4868409499B124F4D15",
      "pub_key": {
        "type": "tendermint/PubKeyEd25519",
        "value": "naltdQ3k0FfMIThKSKpWtSlDcxBPwRrK7jbyfa287Jk="
      },
      "power": "4285714",
      "name": "mbp-v1"
    },
    {
      "address": "9F5F2FD694758F3B6FD20615A29FFF1444A58E85",
      "pub_key": {
        "type": "tendermint/PubKeyEd25519",
        "value": "SzwVs61502OTEhChsUWRvMqo1/ZNrt3gIZpIcojeIus="
      },
      "power": "4285714",
      "name": "mbp-v2"
    },
    {
      "address": "3A3132F8BD1A7972243940070C4EF459A174C366",
      "pub_key": {
        "type": "tendermint/PubKeyEd25519",
        "value": "U4SmbGDMDX7QT2C3zx6yXHSlYn029tPwLBGa40h/LWY="
      },
      "power": "4285714",
      "name": "mbp-v3"
    },
    {
      "address": "32D2DCBAFD6A7455B7E311B63EA14F6ED9F6428F",
      "pub_key": {
        "type": "tendermint/PubKeyEd25519",
        "value": "bVEiyc61162DTmaPhPrcgrhIY01UrNrl4u//P30H+Gk="
      },
      "power": "4285714",
      "name": "mbp-v4"
    },
    {
      "address": "ADD1852F766AA4BD32DA362473DD2FD5262C03D6",
      "pub_key": {
        "type": "tendermint/PubKeyEd25519",
        "value": "DyBBAxu31H0V7yzkg3mm48i08+ycuj2doWj0xMzzw/8="
      },
      "power": "4285714",
      "name": "mini1-v5"
    },
    {
      "address": "3CEB6C9FA26546642409EFE258D9876D163932B7",
      "pub_key": {
        "type": "tendermint/PubKeyEd25519",
        "value": "9vgWs72mJbXEDIqgRFTRJYywsbTWY7c2tIscFRBIA+k="
      },
      "power": "4285714",
      "name": "mini1-v6"
    },
    {
      "address": "E33FDEFF16D34646EF956B8DA05EB63DFD3B737A",
      "pub_key": {
        "type": "tendermint/PubKeyEd25519",
        "value": "gYX5n/VOThUEmAXXqBktk9CaT8K4ACM+I5F2TF6Oqq4="
      },
      "power": "4285714",
      "name": "mini1-v7"
    },
    {
      "address": "91B64E0D9A312641787BDAD4E70B9FEFBB2B4967",
      "pub_key": {
        "type": "tendermint/PubKeyEd25519",
        "value": "ids0Js6DtLwriJsZzlpgAm0LhU2Zm/twRVbRf3AofrE="
      },
      "power": "4285714",
      "name": "mini1-v8"
    },
    {
      "address": "CD5895F8F7993C19AA18B9D6A8DD74D631B339B0",
      "pub_key": {
        "type": "tendermint/PubKeyEd25519",
        "value": "9TUyZcdD++bLR1A6UMw0BkvEAr2APZiajCTA724k1m0="
      },
      "power": "4285714",
      "name": "mini1-v9"
    },
    {
      "address": "77ED89561E2E4C14A1DE4168BBF4FB99DDA0DCF8",
      "pub_key": {
        "type": "tendermint/PubKeyEd25519",
        "value": "IG1IUsdxdEwfsBaTdLqf799aUTo/iV2taEbz8+IWgfY="
      },
      "power": "4285714",
      "name": "mini1-v10"
    },
    {
      "address": "907325BD875319142E793B9C5C2714B0C0390245",
      "pub_key": {
        "type": "tendermint/PubKeyEd25519",
        "value": "N0U/DaqFQY1H0ybCnUlO8D9WY38/you/i8YRzRow3Ec="
      },
      "power": "4285714",
      "name": "mini1-v11"
    },
    {
      "address": "C02B717FA9E93BA02586E1523FDDCA809BF4A1F2",
      "pub_key": {
        "type": "tendermint/PubKeyEd25519",
        "value": "3tvrKpNhHu2gXSWRwcLp1tpK/UTUEE6WoiM7vuwJBLI="
      },
      "power": "4285714",
      "name": "mini1-v12"
    },
    {
      "address": "7BA72D6952FC0D276D9FED8431F26DB147DAF907",
      "pub_key": {
        "type": "tendermint/PubKeyEd25519",
        "value": "ZfXxcFWqTs4F1SKjGWIdvSKXy3YApek8cXL/ID9xEIY="
      },
      "power": "4285714",
      "name": "mini1-v13"
    },
    {
      "address": "F9E124A4199D5CC7B18DB4A4332A55DCF39489E9",
      "pub_key": {
        "type": "tendermint/PubKeyEd25519",
        "value": "8qIXtBmbmFEg17QaVb4ijOSVzGixAzt6JeUDu0xCMao="
      },
      "power": "4285714",
      "name": "mini1-v14"
    },
    {
      "address": "8350D0AD73BC9D73DF5BCC173656E573C54125E8",
      "pub_key": {
        "type": "tendermint/PubKeyEd25519",
        "value": "KjidgBULsYqIi1Y7kIcxgDe7e81ip70W5Ue8waD8KVY="
      },
      "power": "4285714",
      "name": "mini2-v15"
    },
    {
      "address": "408BA74EBA9C2A803EA4D09E105BD8A5852D7CD3",
      "pub_key": {
        "type": "tendermint/PubKeyEd25519",
        "value": "CRA6FNceJ4QhVX2lV48cESV3psjFLnS1HLN/eIwvd+0="
      },
      "power": "4285714",
      "name": "mini2-v16"
    },
    {
      "address": "6AC1C504E161800B4738A2523480311450116BBA",
      "pub_key": {
        "type": "tendermint/PubKeyEd25519",
        "value": "kH1qFfX3r4yjpvAboLSM9EyFl6uQEXq/XmGzrAhnW/I="
      },
      "power": "4285714",
      "name": "mini2-v17"
    },
    {
      "address": "DB5F7C94C33586E81F9A9F186C5FDEBA1B64E9DD",
      "pub_key": {
        "type": "tendermint/PubKeyEd25519",
        "value": "j9XnwjuxE/sUBA7uJ6YXyd/J+1vNWvg/E8psAn1SX1w="
      },
      "power": "4285714",
      "name": "mini2-v18"
    },
    {
      "address": "3A71A14086087DA0F1F6FB023EF68282FA575DBF",
      "pub_key": {
        "type": "tendermint/PubKeyEd25519",
        "value": "BRqP6oPGI9jTxMvwFOkrl/g8obKhJgYkJCakbtsInzU="
      },
      "power": "4285714",
      "name": "mini2-v19"
    },
    {
      "address": "9D9ABBE20B8A416B921EB6BD6505359218DDD43B",
      "pub_key": {
        "type": "tendermint/PubKeyEd25519",
        "value": "l5IoRFDNugwPEHsDGPJ4jeBKdBJ7QDj9dm+x4S+IG+k="
      },
      "power": "4285714",
      "name": "mini2-v20"
    },
    {
      "address": "409ECE8859AC4C65E459DBDBC4B0F18EB66FB442",
      "pub_key": {
        "type": "tendermint/PubKeyEd25519",
        "value": "7WE49KXyE3EwxosQ1vhXYZo6i1UPz/lj0EYVVHA4fEI="
      },
      "power": "4285714",
      "name": "mini2-v21"
    },
    {
      "address": "FCE4FA0ACA8F0EA8CDAFF023268967E3CC805E69",
      "pub_key": {
        "type": "tendermint/PubKeyEd25519",
        "value": "Xg7+l5SsrrB1XQvc8UGegZN3zET3NZWz47wJQEUCVfU="
      },
      "power": "4285714",
      "name": "mini2-v22"
    },
    {
      "address": "ED9B599BE7C8DE2E7BA8374F4C6F51018E71EF39",
      "pub_key": {
        "type": "tendermint/PubKeyEd25519",
        "value": "hn81G2HUb/UxBE+73oVw4zHjfF6Tprzt1Xb9tZAse70="
      },
      "power": "4285714",
      "name": "mini2-v23"
    },
    {
      "address": "1CC136CF1D2CD4B5C3433DA4F2C90EECE95F0711",
      "pub_key": {
        "type": "tendermint/PubKeyEd25519",
        "value": "xSuoz47gOu5x/ww+6sKS28XPV12OFLmz8tJJzJ4sfGc="
      },
      "power": "4285714",
      "name": "mini2-v24"
    },
    {
      "address": "C1A576B8C928E23F3038FA408716F2BE6304B158",
      "pub_key": {
        "type": "tendermint/PubKeyEd25519",
        "value": "8lrRKc1OwdUCkO44LYKXBtbtQosOPB4jwNBh14s5fY8="
      },
      "power": "4285714",
      "name": "mini3-v25"
    },
    {
      "address": "AB40E8A94370EE3B43FBF9166B7AE7AF3A068128",
      "pub_key": {
        "type": "tendermint/PubKeyEd25519",
        "value": "eUxml13l+D/QRDGTpbwtwfh9q84aCXsRQOcXyU+srWY="
      },
      "power": "4285714",
      "name": "mini3-v26"
    },
    {
      "address": "D85504F3CB3FCE35005DC81659F5DDA1FC54E8DE",
      "pub_key": {
        "type": "tendermint/PubKeyEd25519",
        "value": "L4vOY7HjE261IHWjo4mblEBdb/8MoXyMtsD3WlNqkSY="
      },
      "power": "4285714",
      "name": "mini3-v27"
    },
    {
      "address": "0BA417BAFAE1852E20287DA1C9DDC7A64DE3FF9C",
      "pub_key": {
        "type": "tendermint/PubKeyEd25519",
        "value": "HxVxSoagomT0ec7P5TIX5w7RULxomvgPPZoYZV7k9AA="
      },
      "power": "4285714",
      "name": "mini3-v28"
    },
    {
      "address": "97F14E4AB14A6FA3ACCF997E6949DB34A39C7C6E",
      "pub_key": {
        "type": "tendermint/PubKeyEd25519",
        "value": "k+JiYUYy4vVw2V7hU0L63/OV1/25kfg+FNRJrCAvUbY="
      },
      "power": "4285714",
      "name": "mini3-v29"
    },
    {
      "address": "D4716FC5C5099862AC5A36B79FB32A19AB9FAFFD",
      "pub_key": {
        "type": "tendermint/PubKeyEd25519",
        "value": "PCeIGnPq1vohcMGyXtJOgqqhqfZ0i/MxSc0IMIxFRuQ="
      },
      "power": "4285714",
      "name": "mini3-v30"
    },
    {
      "address": "6711FC6F3D380A0F62AD19685DC1BBC7E7A27145",
      "pub_key": {
        "type": "tendermint/PubKeyEd25519",
        "value": "OnuRVjCw2aBgBsiwi0GjhND9yNWYS4TqABuWIxlVfj0="
      },
      "power": "4285714",
      "name": "mini3-v31"
    },
    {
      "address": "6F83847E42F9960C7418154A4080BB5BF832B33B",
      "pub_key": {
        "type": "tendermint/PubKeyEd25519",
        "value": "ir67p/ULOkV8rH7gnGxQSqGjmO5Ye8SpksvZYg82F6U="
      },
      "power": "4285714",
      "name": "mini3-v32"
    },
    {
      "address": "6996B702DA1E95B97FCED3900CCCAFCC07211717",
      "pub_key": {
        "type": "tendermint/PubKeyEd25519",
        "value": "HJ0CknR+noqlaK0ZfFu+0re52lgK5nkGrUriizVTaSs="
      },
      "power": "4285714",
      "name": "mini3-v33"
    },
    {
      "address": "E45929601F4003D62B3457F93CCE623F8A3A5A2E",
      "pub_key": {
        "type": "tendermint/PubKeyEd25519",
        "value": "GbLEP1FSic2s9qCP6muDKj9xd4tFhVwEIwbi3vwl51g="
      },
      "power": "4285714",
      "name": "mini3-v34"
    }
  ],
  "app_hash": "",
  "app_state": {
    "chainId": "ensoul-1",
    "timestamp": 1774222612525,
    "totalSupply": "1000000000000000000000000000",
    "allocations": [
      {
        "label": "Foundation Validator",
        "percentage": 15,
        "tokens": "4285724000000000000000000",
        "recipient": "did:key:z6MkiewFKEurCmchb4HV98oD3Rjbw4yqxQGnivYJ6otzLF7X",
        "autoStake": true
      },
      {
        "label": "Foundation Validator",
        "percentage": 0,
        "tokens": "4285714000000000000000000",
        "recipient": "did:key:z6Mkq4htxWS8jyLz3jjtDGtU36cXvE3kbXa9FTbF4xpPmr4g"
      },
      {
        "label": "Foundation Validator",
        "percentage": 0,
        "tokens": "4285714000000000000000000",
        "recipient": "did:key:z6MkjWwm9vRwo25R8GCDFQmgCvXkKcG5AZGeCj5SSQeQuW9Q"
      },
      {
        "label": "Foundation Validator",
        "percentage": 0,
        "tokens": "4285714000000000000000000",
        "recipient": "did:key:z6Mkk5HCbmULHwL6iDcVfNgsm5kzWQVFwGeupQqDw9D6SMpy"
      },
      {
        "label": "Foundation Validator",
        "percentage": 0,
        "tokens": "4285714000000000000000000",
        "recipient": "did:key:z6MkmozExkxmdrSXtnhPeaSujw7KHtrP9gftBGjvVH7ZE3ZS"
      },
      {
        "label": "Foundation Validator",
        "percentage": 0,
        "tokens": "4285714000000000000000000",
        "recipient": "did:key:z6MkfUJgmfDw9ipEtUEj1aM2KzvcL5V35YPfzeCqnhprH6pv",
        "autoStake": true
      },
      {
        "label": "Foundation Validator",
        "percentage": 0,
        "tokens": "4285714000000000000000000",
        "recipient": "did:key:z6Mkw5KkTJc3dZdMA47E71JavngQ4CDcL8qrmPEEBcc7p464"
      },
      {
        "label": "Foundation Validator",
        "percentage": 0,
        "tokens": "4285714000000000000000000",
        "recipient": "did:key:z6MkoAs8JdFnQ3sDkhDGr1QyroUmVj5BMwXL1DzVLzRDyvJZ"
      },
      {
        "label": "Foundation Validator",
        "percentage": 0,
        "tokens": "4285714000000000000000000",
        "recipient": "did:key:z6MkojPmKYrzFuoMqRVYrp4cdGsA4xsXdJ1vKkUmhKqn57Dr"
      },
      {
        "label": "Foundation Validator",
        "percentage": 0,
        "tokens": "4285714000000000000000000",
        "recipient": "did:key:z6MkvxSyjdy7MZd4WmR3vQQsZaaDsLKvRfgYXjerKyF76b8g"
      },
      {
        "label": "Foundation Validator",
        "percentage": 0,
        "tokens": "4285714000000000000000000",
        "recipient": "did:key:z6Mkgdqjyiwiie9hCy9hPkGmp2y8dtMUrgPvguy1wgtAHye5"
      },
      {
        "label": "Foundation Validator",
        "percentage": 0,
        "tokens": "4285714000000000000000000",
        "recipient": "did:key:z6MkiB1iAqVCcFPm3PyZmFqmtQqN8UMWxWw3YuzC1HPzrsKt"
      },
      {
        "label": "Foundation Validator",
        "percentage": 0,
        "tokens": "4285714000000000000000000",
        "recipient": "did:key:z6MkuTD3waVwDJnUq8eChVNdGN4LHp5xJqrbgyQUydqTDH5B"
      },
      {
        "label": "Foundation Validator",
        "percentage": 0,
        "tokens": "4285714000000000000000000",
        "recipient": "did:key:z6MkmKGjf9oGWbF3oSgSDwJ3AFpgsY8eGtszf2F22p41Rnry"
      },
      {
        "label": "Foundation Validator",
        "percentage": 0,
        "tokens": "4285714000000000000000000",
        "recipient": "did:key:z6MkvnQ4f36mPWiWKwy5EE2enreynbFw2YpmThAL68ECwsU5"
      },
      {
        "label": "Foundation Validator",
        "percentage": 0,
        "tokens": "4285714000000000000000000",
        "recipient": "did:key:z6MkhJ5ErDvgXp1wpmSW55sDpbBxXJ9o4dGE9Ukue77rPSaR",
        "autoStake": true
      },
      {
        "label": "Foundation Validator",
        "percentage": 0,
        "tokens": "4285714000000000000000000",
        "recipient": "did:key:z6Mkf4e4mvWEbCM2HEhaU1QDo83wkdey8ZpEdJvFwekdAXbz"
      },
      {
        "label": "Foundation Validator",
        "percentage": 0,
        "tokens": "4285714000000000000000000",
        "recipient": "did:key:z6MkpBHfsncKdRic3mrGRDsdfGRz76FoQs6EYDMzXw9YyNbT"
      },
      {
        "label": "Foundation Validator",
        "percentage": 0,
        "tokens": "4285714000000000000000000",
        "recipient": "did:key:z6Mkp8jXR22REXjXAu8m1twNKGr9LAxdn9koqgDqWAZNFAbd"
      },
      {
        "label": "Foundation Validator",
        "percentage": 0,
        "tokens": "4285714000000000000000000",
        "recipient": "did:key:z6MkeoBaLsJ2LTVQiZUwFQAS4zqxh5XsphqabEQpoTUdSzap"
      },
      {
        "label": "Foundation Validator",
        "percentage": 0,
        "tokens": "4285714000000000000000000",
        "recipient": "did:key:z6MkpevsRF15MoNqs7ps1putD7vwfWGfgsvB48kGCPFt6XcC"
      },
      {
        "label": "Foundation Validator",
        "percentage": 0,
        "tokens": "4285714000000000000000000",
        "recipient": "did:key:z6MkvRteszWtf5iWuHidJoaQ3SDsfrcPFEf6KxfCgCkLUkjj"
      },
      {
        "label": "Foundation Validator",
        "percentage": 0,
        "tokens": "4285714000000000000000000",
        "recipient": "did:key:z6MkknRdWX6CK6Y4zqqrEFxSUFa2p48cC742AYuX5PoQHusa"
      },
      {
        "label": "Foundation Validator",
        "percentage": 0,
        "tokens": "4285714000000000000000000",
        "recipient": "did:key:z6MkoWHBPQoeZAohxv83oemmh2tuF1XVa73jjbDGSk6Gx33S"
      },
      {
        "label": "Foundation Validator",
        "percentage": 0,
        "tokens": "4285714000000000000000000",
        "recipient": "did:key:z6MksivyUdiNUhJWMxgSnzhvPLTSHUVZjZA8X6i72kyZ9KV8"
      },
      {
        "label": "Foundation Validator",
        "percentage": 0,
        "tokens": "4285714000000000000000000",
        "recipient": "did:key:z6MkvmK2YQ9GzUJKfQzhmfwoEtmT2GQTLKqa941GSMszSb3U",
        "autoStake": true
      },
      {
        "label": "Foundation Validator",
        "percentage": 0,
        "tokens": "4285714000000000000000000",
        "recipient": "did:key:z6MknckwpzNtccdbwC85Z4T1Lb2H9yn9E6BDqNgxCnRgCsoB"
      },
      {
        "label": "Foundation Validator",
        "percentage": 0,
        "tokens": "4285714000000000000000000",
        "recipient": "did:key:z6MkherrQNyVe5WykdW6vJpXiDdEMekGvaoBPW4WDzvqXoRo"
      },
      {
        "label": "Foundation Validator",
        "percentage": 0,
        "tokens": "4285714000000000000000000",
        "recipient": "did:key:z6MkgYbeY93qhEDVRD1mSYkKdshrJsXHjjZfjGBVtXrUf9Rq"
      },
      {
        "label": "Foundation Validator",
        "percentage": 0,
        "tokens": "4285714000000000000000000",
        "recipient": "did:key:z6MkpQYC7it5pRmbjKaiN3wqf4xpz5PY5eBPqiD7d3oEEbkR"
      },
      {
        "label": "Foundation Validator",
        "percentage": 0,
        "tokens": "4285714000000000000000000",
        "recipient": "did:key:z6MkiW5UB7Xh2tPUstUNJTDYGUYwRE7LjtydWm2RWVoR3E9q"
      },
      {
        "label": "Foundation Validator",
        "percentage": 0,
        "tokens": "4285714000000000000000000",
        "recipient": "did:key:z6MkiPYyZ5P75AY72FcBvzLMVdGnnyptoXvwp6zJjPPSEt1z"
      },
      {
        "label": "Foundation Validator",
        "percentage": 0,
        "tokens": "4285714000000000000000000",
        "recipient": "did:key:z6MkonrzYoqNqD7iL87xz8Ppqrjtq73xYWaxA3pYxevURvDi"
      },
      {
        "label": "Foundation Validator",
        "percentage": 0,
        "tokens": "4285714000000000000000000",
        "recipient": "did:key:z6MkgNxKbmse6px1xeXr1C2L53LXD6zUoCdxsHRygcYfUkXU"
      },
      {
        "label": "Foundation Validator",
        "percentage": 0,
        "tokens": "4285714000000000000000000",
        "recipient": "did:key:z6MkgBaLg2KEK5bGcAax2PeVp1n6hJvBzM6ZRjMPrfwPQS1V"
      },
      {
        "label": "Network Rewards",
        "percentage": 50,
        "tokens": "500000000000000000000000000",
        "recipient": "did:ensoul:protocol:rewards"
      },
      {
        "label": "Protocol Treasury",
        "percentage": 10,
        "tokens": "100000000000000000000000000",
        "recipient": "did:key:z6Mki9jwpYMBB93zxYfsmNUHThpSgKATqydN4xJA1xcxGecm"
      },
      {
        "label": "Agent Onboarding",
        "percentage": 10,
        "tokens": "100000000000000000000000000",
        "recipient": "did:key:z6MkhyWUyAgAcs4Sv5AHfwqkyfnov1kLGj42VC7NvK9kcotf"
      },
      {
        "label": "Initial Liquidity",
        "percentage": 5,
        "tokens": "50000000000000000000000000",
        "recipient": "did:key:z6MkepCt389w2K5p8MrU4paUgrvr5EAYHg8MjUhdRiCTjsGz"
      },
      {
        "label": "Early Contributors",
        "percentage": 5,
        "tokens": "50000000000000000000000000",
        "recipient": "did:key:z6MkpkBGr18AkgAipmmtXCU9kPz11f2bVtSDG2p471F31imL"
      },
      {
        "label": "Insurance Reserve",
        "percentage": 5,
        "tokens": "50000000000000000000000000",
        "recipient": "did:key:z6MkjNGivywrX7nmUE9aiAfjqDU97fdJBw15y61X4DpgawMV"
      }
    ],
    "emissionPerBlock": "19025875190258751902",
    "networkRewardsPool": "500000000000000000000000000",
    "protocolFees": {
      "storageFeeProtocolShare": 10,
      "txBaseFee": "1000"
    }
  }
}